hx_markup/__init__.py
hx_markup/config.py
hx_markup/element.py
hx_markup/enums.py
hx_markup/functions.py
hx_markup-0.2.2.dist-info/WHEEL
hx_markup-0.2.2.dist-info/METADATA
hx_markup-0.2.2.dist-info/RECORD
